pytest_pg/__init__.py
pytest_pg/fixtures.py
pytest_pg/py.typed
pytest_pg/utils.py
pytest_pg-0.0.25.dist-info/licenses/LICENSE
pytest_pg-0.0.25.dist-info/METADATA
pytest_pg-0.0.25.dist-info/WHEEL
pytest_pg-0.0.25.dist-info/entry_points.txt
pytest_pg-0.0.25.dist-info/top_level.txt
pytest_pg-0.0.25.dist-info/RECORD
