Metadata-Version: 2.4
Name: pytest_pg
Version: 0.0.25
Summary: A tiny plugin for pytest which runs PostgreSQL in Docker
Home-page: https://github.com/anna-money/pytest-pg
Author: Yury Pliner
Author-email: yury.pliner@gmail.com
License: MIT
Platform: macOS
Platform: POSIX
Platform: Windows
Classifier: License :: OSI Approved :: MIT License
Classifier: Intended Audience :: Developers
Classifier: Programming Language :: Python :: 3
Classifier: Programming Language :: Python :: 3 :: Only
Classifier: Programming Language :: Python :: 3.9
Classifier: Programming Language :: Python :: 3.10
Classifier: Programming Language :: Python :: 3.11
Classifier: Programming Language :: Python :: 3.12
Classifier: Programming Language :: Python :: 3.13
Classifier: Operating System :: OS Independent
Classifier: Development Status :: 5 - Production/Stable
Classifier: Framework :: Pytest
Requires-Python: >=3.9
License-File: LICENSE
Requires-Dist: docker>=7.0.0
Requires-Dist: pytest>=7.4
Dynamic: author
Dynamic: author-email
Dynamic: classifier
Dynamic: description
Dynamic: description-content-type
Dynamic: home-page
Dynamic: license
Dynamic: license-file
Dynamic: platform
Dynamic: requires-dist
Dynamic: requires-python
Dynamic: summary
